{
  "gitSyncId": "6a44d0f9af138a374389db91_7a317790-a1df-40fa-9622-c4553aacd375",
  "id": "Main Menu_formHandlers.resetForm",
  "pluginId": "js-plugin",
  "pluginType": "JS",
  "unpublishedAction": {
    "actionConfiguration": {
      "encodeParamsToggle": true,
      "jsArguments": [],
      "paginationType": "NONE",
      "timeoutInMillisecond": 10000
    },
    "collectionId": "Main Menu_formHandlers",
    "confirmBeforeExecute": false,
    "datasource": {
      "isAutoGenerated": false,
      "name": "UNUSED_DATASOURCE",
      "pluginId": "js-plugin"
    },
    "dynamicBindingPathList": [
      {
        "key": "body"
      }
    ],
    "fullyQualifiedName": "formHandlers.resetForm",
    "name": "resetForm",
    "pageId": "Main Menu",
    "runBehaviour": "MANUAL",
    "userSetOnLoad": false
  }
}