{
  "gitSyncId": "6a44afdb8905c61a90ad7cd6_1631ef88-bfbb-404a-97c9-07739cca753f",
  "id": "Page1_getAllComponents",
  "pluginId": "postgres-plugin",
  "pluginType": "DB",
  "unpublishedAction": {
    "actionConfiguration": {
      "body": "SELECT \n    c.id,\n    c.part_number,\n    c.category_id,\n    cat.name as category_name,\n    c.manufacturer_id,\n    m.name as manufacturer_name,\n    c.package,\n    c.package_id,\n    ps.name as package_standard_name,\n    c.value_number,\n    c.value_multiplier,\n    c.value_unit,\n    c.value_display,\n    c.tolerance_percent,\n    c.voltage_rating_v,\n    c.power_rating_w,\n    c.temp_min_c,\n    c.temp_max_c,\n    c.library_path,\n    c.library_ref,\n    c.footprint_path,\n    c.footprint_ref,\n    c.datasheet_url,\n    c.spice_model_path,\n    c.altium_comment,\n    c.altium_designator,\n    c.kicad_keywords,\n    c.kicad_fp_filter\nFROM components c\nLEFT JOIN categories cat ON c.category_id = cat.id\nLEFT JOIN manufacturers m ON c.manufacturer_id = m.id\nLEFT JOIN packages pkg ON c.package_id = pkg.id\nLEFT JOIN package_standards ps ON pkg.standard_id = ps.id\nORDER BY c.id DESC",
      "encodeParamsToggle": true,
      "paginationType": "NONE",
      "pluginSpecifiedTemplates": [
        {
          "value": true
        }
      ],
      "timeoutInMillisecond": 10000
    },
    "confirmBeforeExecute": false,
    "datasource": {
      "id": "Altium",
      "isAutoGenerated": false,
      "name": "Altium",
      "pluginId": "postgres-plugin"
    },
    "dynamicBindingPathList": [],
    "name": "getAllComponents",
    "pageId": "Page1",
    "runBehaviour": "AUTOMATIC",
    "userSetOnLoad": false
  }
}